{"StSy6+6RZjcYqx/xoWHl6g==":"47370986-533711457040933-7053368273299046400-n.jpg","tuoOOvRlYz2vDO6oCoAM1g==":"47370986-533711457040933-7053368273299046400-n.jpeg","Ji5YnC0XL64mscQSh/Z+9w==":"cover.png","J9sCiQOfyDz6y3kzjsoG5A==":"cover-1.png","5vib2LBVuViIIHj8g8jsCg==":"cover-2.png","PMUU0fKAXRZP4gjWemzgnw==":"cover-3.png","AABroQKXx/Y8hDwe5SDirA==":"cover-512x512.png","XEY6DV7T36DIf/+ohcwqWw==":"cover-2-480x480.png","UAc7kepzJPkrSn4uqTRvmw==":"background4.jpg","mIIbxW0r7dEZSbMPwcoYdg==":"background2.jpg","pa5Dkwo/T1qgW/t0h+fQvA==":"background5.jpg","sT80Y4RCGNBrSInGgrjIuA==":"background3.jpg","7/oW0P4kpBvA0LKZqscPhw==":"forestfight1.png","Ult8y2KzR4Hzx12e/doNuw==":"forestfight3.png","f38ZNSP0ApiYQGSfKQGqyQ==":"forestfight2.png","IeumwTN/SrwfMQTrfddScQ==":"stack1.png","64EFPi+3ajb8gKLh01PJ5w==":"stack2.png","uo89r5CXLD1TTTMyqV4phg==":"stack3.png","68aESTZKE9H9cDExrMBVSw==":"knossos1.png","FW40k1PARdUrWtx9kCVqeg==":"knossos2.png","FMVLCMXyzTs5MgK6B5M70Q==":"extrusion1.png","U2zc9tXzPaCmCejOXifuGw==":"extrusion2.png","iLs1GbzEua+AhNwcsGn9Og==":"extrusion3.png","Cgtke09dI6fK3Ufs4nB2gQ==":"push3.png","YDBTFrQ0i561o0C5hPQTFQ==":"push1.png","Q6J/CZ1JMgSO4ReozbYE9Q==":"push2.png","CPNVIpGPuP1ndZ/kkU2BtQ==":"42306142-945039985687828-7077680120361648128-n.jpg","YA4P7U8atslEvLFuYEj/IA==":"hax.jpg","pZy4W8Ux59bsjrtjhjokJw==":"blank-diagram.png","U6UbR8VpGSvBHnErFmriuA==":"enviro-concept1.jpg","cUws2b3D4kEX7cIOmwv3mg==":"enviro-concept1.jpeg","c1i6VTZ0Vd37tb5JmU9rew==":"stack3-1.png","yFhRVt7nU1j++Eo8DVB4pg==":"stack3-2.png","uqM8NsOYivMMCq8SnIPdNQ==":"stack3-3.png","xk8qq5noMqTPheqOoeRqYA==":"blossom-64-bit-development-pcd3d-sm5-12-20-2020-2-56-10-pm.png","R7N2c5MV1DwBvjM3YcyOdg==":"blossom-64-bit-development-pcd3d-sm5-12-20-2020-3-01-19-pm.png","ssP5pzTTlnl/9B6R1ygSag==":"blossom-64-bit-development-pcd3d-sm5-12-20-2020-3-00-15-pm-1.png","BB52+LizbPwpGWqfUii/iw==":"title.png","fB+bH85aqz9wcFU9LKH9xw==":"medusa-screenshot-1.png","EHetkyaujbqVZzGzOsKf6A==":"medusa-screenshot-2.png","zNAQNGWXMCha7EmwRf2Jaw==":"medusa-screenshot-3.png","OM6hTwqMAQpTVhLcPG86xg==":"background1.jpg","oJpRcNWncWglbxDLoRXEow==":"title-800x800.png","mD4fIJh0QxHqR+3Be6o8/A==":"enviro-concept1-1.jpeg","rhS9Tib4p6MB68vu204fgQ==":"47370986-533711457040933-7053368273299046400-n-1.jpeg","gSlYQ4XVjKpsg0D681k5Sg==":"enviro-concept1.jpg","SZzxjHDSbonHSRnkcSN9ow==":"blossom-64-bit-development-pcd3d-sm5-12-20-2020-2-56-10-pm.png","ueSoDvvwCuEuQib2J+df9A==":"blossom-64-bit-development-pcd3d-sm5-12-20-2020-3-00-15-pm-1.png","NsGlDExfwPqkc2FF/a7WxA==":"blossom-64-bit-development-pcd3d-sm5-12-20-2020-3-01-19-pm.png","QmC58Gqe6PmliBEHvKFoWQ==":"cover-1.png","uTybcwI+CE/gLuRrwtsfAw==":"stack1.png","o4sEeHK46VOM2P06Z2JmZQ==":"stack2.png","040fFp/2HAZfN0oG1ufueQ==":"stack3-3.png","4wGQ93OY1mcbACKAESlSaw==":"cover-2.png","7m2WbM7tih8Ct0wnoFU9BA==":"extrusion1.png","f1FrXkZp4ij3bib+lYVy8Q==":"extrusion2.png","i0cJK0s5UGuAttUbHAgwKw==":"extrusion3.png","QpivdUDWsBmmj+amsKLpoQ==":"cover-3.png","iZ8ZAgVi4JWzmqAP2UK6uQ==":"push3.png","gQIX+R//LAo5oT16x/97jQ==":"push1.png","xFohPeFpKG/R9z9cFSYz1Q==":"push2.png","dxEqqJ4OxjmJhxIpX2RKjg==":"enviro-concept1.jpeg","0CBk9eOZ5qoqoXjcmZxHPA==":"forestfight3.png","41Fx3ldovL+S8MB0Vs0kcQ==":"forestfight1.png","VSHgK12QjI+hequkc2icLQ==":"forestfight2.png","BtDALXkx86Lrr2vNytx2Kg==":"47370986-533711457040933-7053368273299046400-n-1.jpeg","qY9g1aiohUWJ/al6P35ZKA==":"logo2-1.png","7vw8LH2xOE6w0MerueyYZQ==":"background4-1.jpg","KpI3bz0ZV81fW8+R/SnKLQ==":"vsulzer.png"}